README.rst
setup.py
worklog/__init__.py
worklog/day_stats_walker.py
worklog/print_worklog_function.py
worklog/process.py
worklog/parsing/WorklogLexer.py
worklog/parsing/WorklogListener.py
worklog/parsing/WorklogParser.py
worklog/parsing/__init__.py
worklog/parsing2/WorklogLexer.py
worklog/parsing2/WorklogListener.py
worklog/parsing2/WorklogParser.py
worklog/parsing2/__init__.py
worklogmd.egg-info/PKG-INFO
worklogmd.egg-info/SOURCES.txt
worklogmd.egg-info/dependency_links.txt
worklogmd.egg-info/entry_points.txt
worklogmd.egg-info/requires.txt
worklogmd.egg-info/top_level.txt