Metadata-Version: 1.0
Name: worklogmd
Version: 0.24
Summary: Text-based work habit tracker
Home-page: https://github.com/ssaamm/worklog.md
Author: Samuel Taylor
Author-email: UNKNOWN
License: MIT
Platform: UNKNOWN
